flatterer-0.23.0.dist-info/METADATA
flatterer-0.23.0.dist-info/WHEEL
flatterer-0.23.0.dist-info/entry_points.txt
flatterer-0.23.0.dist-info/licenses/LICENSE
flatterer/__init__.py
flatterer/flatterer.cpython-311-x86_64-linux-gnu.so
flatterer/static/assets/index.824ae5b0.css
flatterer/static/assets/index.84e0a51b.js
flatterer/static/assets/materialdesignicons-webfont.48d3eec6.woff
flatterer/static/assets/materialdesignicons-webfont.861aea05.eot
flatterer/static/assets/materialdesignicons-webfont.bd725a7a.ttf
flatterer/static/assets/materialdesignicons-webfont.e52d60f6.woff2
flatterer/static/assets/webfontloader.b777d690.js
flatterer/static/favicon/android-chrome-192x192.png
flatterer/static/favicon/android-chrome-512x512.png
flatterer/static/favicon/apple-touch-icon.png
flatterer/static/favicon/browserconfig.xml
flatterer/static/favicon/favicon-16x16.png
flatterer/static/favicon/favicon-32x32.png
flatterer/static/favicon/favicon.ico
flatterer/static/favicon/mstile-150x150.png
flatterer/static/favicon/safari-pinned-tab.svg
flatterer/static/favicon/site.webmanifest
flatterer/static/index.html
flatterer/tests.py
flatterer-0.23.0.dist-info/RECORD
