Metadata-Version: 2.4
Name: flatterer
Version: 0.23.0
Requires-Dist: orjson
Requires-Dist: ijson
Requires-Dist: click
Requires-Dist: pandas
License-File: LICENSE
Summary: Opinionated JSON to CSV converter
Author: David Raznick <kindly@gmail.com>
Author-email: David Raznick <kindly@gmail.com>
License: License :: OSI Approved :: MIT License
